[
  {
    "artist": "F. Godi",
    "title": "Peacock Strut"
  },
  {
    "artist": "Yoko Ono, The Plastic Ono Band, Elephants Memory",
    "title": "Have You Seen A Horizon Lately"
  },
  {
    "artist": "Little Ann",
    "title": "Deep Shadows"
  },
  {
    "artist": "Alan Hackshaw",
    "title": "Girl In A Sports Car"
  },
  {
    "artist": "Lee Hazelwood",
    "title": "Hey Cowboy"
  },
  {
    "artist": "Unknown Artist",
    "title": "Tape Machine Lofi Ambient Demo Tascam"
  },
  {
    "artist": "Minoru ” Hoodoo” Fushimi",
    "title": "Thanatopsis"
  },
  {
    "artist": "Wings",
    "title": "She’s My Baby"
  },
  {
    "artist": "Larry Page",
    "title": "Do It In Slow Motion"
  },
  {
    "artist": "Sly & The Family Stone",
    "title": "Thankful N' Thoughtful"
  },
  {
    "artist": "T. Hymas",
    "title": "Final Inspection"
  },
  {
    "artist": "A Frydman & M. Cannone",
    "title": "Jardin D’enfants"
  },
  {
    "artist": "Haindling",
    "title": "I Mog Di"
  },
  {
    "artist": "Ryo",
    "title": "Hawaiian Caravan"
  },
  {
    "artist": "Eden Ahbez \"Nature Boy\"",
    "title": "Market Place"
  },
  {
    "artist": "Akiko Yano",
    "title": "Kaze Wo Atsumete"
  }
]